Metadata-Version: 2.1
Name: customized-distributions
Version: 0.1
Summary: Gaussian and Binomial distributions
Home-page: UNKNOWN
Author: Arun A Menon
Author-email: arun.sunshine.menon@gmail.com
License: UNKNOWN
Platform: UNKNOWN
